AIFoundationKit/__init__.py
AIFoundationKit/agentic/__init__.py
AIFoundationKit/base/__init__.py
AIFoundationKit/base/file_manager.py
AIFoundationKit/base/model.py
AIFoundationKit/base/utils.py
AIFoundationKit/base/exception/__init__.py
AIFoundationKit/base/exception/custom_exception.py
AIFoundationKit/base/logger/__init__.py
AIFoundationKit/base/logger/custom_logger.py
AIFoundationKit/base/logger/logger_utils.py
AIFoundationKit/dl/__init__.py
AIFoundationKit/genai/__init__.py
AIFoundationKit/ml/__init__.py
AIFoundationKit/rag/__init__.py
AIFoundationKit/rag/model_loader.py
AIFoundationKit/rag/prompts/__init__.py
AIFoundationKit/rag/prompts/generic_prompts.py
ai_foundation_kit-0.1.6.dist-info/licenses/LICENSE
ai_foundation_kit-0.1.6.dist-info/METADATA
ai_foundation_kit-0.1.6.dist-info/WHEEL
ai_foundation_kit-0.1.6.dist-info/top_level.txt
ai_foundation_kit-0.1.6.dist-info/RECORD
